pysheds/__init__.py
pysheds/_sgrid.py
pysheds/_sview.py
pysheds/grid.py
pysheds/io.py
pysheds/pgrid.py
pysheds/projection.py
pysheds/pview.py
pysheds/rfsm.py
pysheds/sgrid.py
pysheds/sview.py
pysheds/view.py
pysheds-0.3.5.dist-info/LICENSE
pysheds-0.3.5.dist-info/METADATA
pysheds-0.3.5.dist-info/WHEEL
pysheds-0.3.5.dist-info/top_level.txt
pysheds-0.3.5.dist-info/RECORD
