Metadata-Version: 2.1
Name: pysheds
Version: 0.3.5
Summary: 🌎 Simple and fast watershed delineation in python.
Home-page: http://open-storm.org
Author: Matt Bartos
Author-email: mdbartos@umich.edu
Classifier: Development Status :: 4 - Beta
Classifier: Intended Audience :: Developers
Classifier: Intended Audience :: Science/Research
Classifier: License :: OSI Approved :: GNU General Public License v3 or later (GPLv3+)
Classifier: Natural Language :: English
Classifier: Operating System :: OS Independent
Classifier: Programming Language :: Python :: 3
Classifier: Programming Language :: Python :: 3.6
Classifier: Programming Language :: Python :: 3.7
Classifier: Programming Language :: Python :: 3.8
Classifier: Programming Language :: Python :: 3.9
Classifier: Programming Language :: Python :: 3.10
Classifier: Programming Language :: Python :: 3.11
Classifier: Topic :: Scientific/Engineering :: GIS
Classifier: Topic :: Scientific/Engineering :: Hydrology
License-File: LICENSE
Requires-Dist: affine
Requires-Dist: geojson
Requires-Dist: numba
Requires-Dist: numpy
Requires-Dist: pandas
Requires-Dist: pyproj
Requires-Dist: rasterio (>=1)
Requires-Dist: scikit-image
Requires-Dist: scipy
Provides-Extra: dev
Requires-Dist: pytest ; extra == 'dev'
Requires-Dist: pytest-cov ; extra == 'dev'
Provides-Extra: recipes
Requires-Dist: geopandas ; extra == 'recipes'
Requires-Dist: ipython ; extra == 'recipes'
Requires-Dist: matplotlib ; extra == 'recipes'
Requires-Dist: seaborn ; extra == 'recipes'
